DataTSE
