Metadata-Version: 1.0
Name: DataTSE
Version: 0.4
Summary: Pacote com funções para uso de dados de eleições do TSE
Home-page: UNKNOWN
Author: Lucas Maretti
Author-email: lucas.maretti@gmail.com
License: UNKNOWN
Platform: UNKNOWN
